[
   {
      "Foldername": "junk_file",
      "filename": "100_",
      "from": "angela.white@enron.com",
      "x-from": "White, Angela"
   },
   {
      "Foldername": "junk_file",
      "filename": "101_",
      "from": "elizabeth.brown@enron.com",
      "x-from": "Brown, Elizabeth"
   },
   {
      "Foldername": "junk_file",
      "filename": "102_",
      "from": "audrey.robertson@enron.com",
      "x-from": "Robertson, Audrey"
   },
   {
      "Foldername": "junk_file",
      "filename": "103_",
      "from": "tk.lohman@enron.com",
      "x-from": "Lohman, TK"
   },
   {
      "Foldername": "junk_file",
      "filename": "104_",
      "from": "penny.mccarran@enron.com",
      "x-from": "McCarran, Penny"
   },
   {
      "Foldername": "junk_file",
      "filename": "105_",
      "from": "newsletter@rigzone.com",
      "x-from": "newsletter@rigzone.com"
   },
   {
      "Foldername": "junk_file",
      "filename": "106_",
      "from": "info@pmaconference.com",
      "x-from": "The Power Marketing Association"
   },
   {
      "Foldername": "junk_file",
      "filename": "107_",
      "from": "events@eyeforenergy.com",
      "x-from": "events@eyeforenergy.com"
   },
   {
      "Foldername": "junk_file",
      "filename": "108_",
      "from": "newsletter@rigzone.com",
      "x-from": "newsletter@rigzone.com"
   },
   {
      "Foldername": "junk_file",
      "filename": "109_",
      "from": "announcements.enron@enron.com",
      "x-from": "Enron General Announcements"
   },
   {
      "Foldername": "junk_file",
      "filename": "10_",
      "from": "michael.bodnar@enron.com",
      "x-from": "Bodnar, Michael"
   },
   {
      "Foldername": "junk_file",
      "filename": "110_",
      "from": "robert.kilmer@enron.com",
      "x-from": "Kilmer III, Robert"
   },
   {
      "Foldername": "junk_file",
      "filename": "111_",
      "from": "info@pmaconference.com",
      "x-from": "The Power Marketing Association"
   },
   {
      "Foldername": "junk_file",
      "filename": "113_",
      "from": "angela.white@enron.com",
      "x-from": "White, Angela"
   },
   {
      "Foldername": "junk_file",
      "filename": "114_",
      "from": "dennis.lee@enron.com",
      "x-from": "Lee, Dennis"
   },
   {
      "Foldername": "junk_file",
      "filename": "115_",
      "from": "sslindberg@duke-energy.com",
      "x-from": "Susan S. Lindberg"
   },
   {
      "Foldername": "junk_file",
      "filename": "116_",
      "from": "angela.white@enron.com",
      "x-from": "White, Angela"
   },
   {
      "Foldername": "junk_file",
      "filename": "117_",
      "from": "elizabeth.brown@enron.com",
      "x-from": "Brown, Elizabeth"
   },
   {
      "Foldername": "junk_file",
      "filename": "118_",
      "from": "dennis.lee@enron.com",
      "x-from": "Lee, Dennis"
   },
   {
      "Foldername": "junk_file",
      "filename": "119_",
      "from": "angela.white@enron.com",
      "x-from": "White, Angela"
   },
   {
      "Foldername": "junk_file",
      "filename": "11_",
      "from": "emily.sellers@enron.com",
      "x-from": "Sellers, Emily"
   },
   {
      "Foldername": "junk_file",
      "filename": "120_",
      "from": "coo.jeff@enron.com",
      "x-from": "Jeff McMahon - President & COO"
   },
   {
      "Foldername": "junk_file",
      "filename": "121_",
      "from": "dennis.lee@enron.com",
      "x-from": "Lee, Dennis"
   },
   {
      "Foldername": "junk_file",
      "filename": "122_",
      "from": "newsletter@rigzone.com",
      "x-from": "newsletter@rigzone.com"
   },
   {
      "Foldername": "junk_file",
      "filename": "124_",
      "from": "ramona.betancourt@enron.com",
      "x-from": "Betancourt, Ramona"
   },
   {
      "Foldername": "junk_file",
      "filename": "125_",
      "from": "announcements.ets@enron.com",
      "x-from": "ETS General Announcements"
   },
   {
      "Foldername": "junk_file",
      "filename": "126_",
      "from": "tk.lohman@enron.com",
      "x-from": "Lohman, TK"
   },
   {
      "Foldername": "junk_file",
      "filename": "127_",
      "from": "ramona.betancourt@enron.com",
      "x-from": "Betancourt, Ramona"
   },
   {
      "Foldername": "junk_file",
      "filename": "128_",
      "from": "angela.white@enron.com",
      "x-from": "White, Angela"
   },
   {
      "Foldername": "junk_file",
      "filename": "129_",
      "from": "dennis.lee@enron.com",
      "x-from": "Lee, Dennis"
   },
   {
      "Foldername": "junk_file",
      "filename": "12_",
      "from": "linda.trevino@enron.com",
      "x-from": "Trevino, Linda"
   },
   {
      "Foldername": "junk_file",
      "filename": "130_",
      "from": "announcements.enron@enron.com",
      "x-from": "Enron General Announcements"
   },
   {
      "Foldername": "junk_file",
      "filename": "131_",
      "from": "jan.moore@enron.com",
      "x-from": "Moore, Jan"
   },
   {
      "Foldername": "junk_file",
      "filename": "132_",
      "from": "jan.moore@enron.com",
      "x-from": "Moore, Jan"
   },
   {
      "Foldername": "junk_file",
      "filename": "133_",
      "from": "glen.hass@enron.com",
      "x-from": "Hass, Glen"
   },
   {
      "Foldername": "junk_file",
      "filename": "134_",
      "from": "center.ets@enron.com",
      "x-from": "ETS Solution Center"
   },
   {
      "Foldername": "junk_file",
      "filename": "135_",
      "from": "announcements.enron@enron.com",
      "x-from": "Enron General Announcements"
   },
   {
      "Foldername": "junk_file",
      "filename": "137_",
      "from": "newsletter@rigzone.com",
      "x-from": "newsletter@rigzone.com"
   },
   {
      "Foldername": "junk_file",
      "filename": "138_",
      "from": "info@pmaconference.com",
      "x-from": "The Power Marketing Association"
   },
   {
      "Foldername": "junk_file",
      "filename": "139_",
      "from": "dennis.lee@enron.com",
      "x-from": "Lee, Dennis"
   },
   {
      "Foldername": "junk_file",
      "filename": "13_",
      "from": "newsletter@rigzone.com",
      "x-from": "newsletter@rigzone.com"
   },
   {
      "Foldername": "junk_file",
      "filename": "140_",
      "from": "angela.white@enron.com",
      "x-from": "White, Angela"
   },
   {
      "Foldername": "junk_file",
      "filename": "141_",
      "from": "audrey.robertson@enron.com",
      "x-from": "Robertson, Audrey"
   },
   {
      "Foldername": "junk_file",
      "filename": "142_",
      "from": "lippmanc@aol.com",
      "x-from": "Lippmanc@aol.com"
   },
   {
      "Foldername": "junk_file",
      "filename": "143_",
      "from": "john@pgsenergy.com",
      "x-from": "John Adamiak"
   },
   {
      "Foldername": "junk_file",
      "filename": "144_",
      "from": "center.ets@enron.com",
      "x-from": "ETS Solution Center"
   },
   {
      "Foldername": "junk_file",
      "filename": "146_",
      "from": "newsletter@rigzone.com",
      "x-from": "newsletter@rigzone.com"
   },
   {
      "Foldername": "junk_file",
      "filename": "147_",
      "from": "info@pmaconference.com",
      "x-from": "The Power Marketing Association"
   },
   {
      "Foldername": "junk_file",
      "filename": "148_",
      "from": "dennis.lee@enron.com",
      "x-from": "Lee, Dennis"
   },
   {
      "Foldername": "junk_file",
      "filename": "149_",
      "from": "dennis.lee@enron.com",
      "x-from": "Lee, Dennis"
   },
   {
      "Foldername": "junk_file",
      "filename": "14_",
      "from": "announcements.ets@enron.com",
      "x-from": "ETS General Announcements"
   },
   {
      "Foldername": "junk_file",
      "filename": "150_",
      "from": "angela.white@enron.com",
      "x-from": "White, Angela"
   },
   {
      "Foldername": "junk_file",
      "filename": "151_",
      "from": "audrey.robertson@enron.com",
      "x-from": "Robertson, Audrey"
   },
   {
      "Foldername": "junk_file",
      "filename": "152_",
      "from": "center.ets@enron.com",
      "x-from": "ETS Solution Center"
   },
   {
      "Foldername": "junk_file",
      "filename": "153_",
      "from": "announcements.ets@enron.com",
      "x-from": "ETS General Announcements"
   },
   {
      "Foldername": "junk_file",
      "filename": "155_",
      "from": "newsletter@rigzone.com",
      "x-from": "newsletter@rigzone.com"
   },
   {
      "Foldername": "junk_file",
      "filename": "156_",
      "from": "info@pmaconference.com",
      "x-from": "The Power Marketing Association"
   },
   {
      "Foldername": "junk_file",
      "filename": "157_",
      "from": "news@eyeforenergy.com",
      "x-from": "Eyeforenergy"
   },
   {
      "Foldername": "junk_file",
      "filename": "158_",
      "from": "jan.moore@enron.com",
      "x-from": "Moore, Jan"
   },
   {
      "Foldername": "junk_file",
      "filename": "15_",
      "from": "rosemary.gracey@enron.com",
      "x-from": "Gracey, Rosemary"
   },
   {
      "Foldername": "junk_file",
      "filename": "160_",
      "from": "10182829@mbox.surecom.com",
      "x-from": "Petroleum Argus"
   },
   {
      "Foldername": "junk_file",
      "filename": "161_",
      "from": "newsletter@rigzone.com",
      "x-from": "newsletter@rigzone.com"
   },
   {
      "Foldername": "junk_file",
      "filename": "162_",
      "from": "info@pmaconference.com",
      "x-from": "The Power Marketing Association"
   },
   {
      "Foldername": "junk_file",
      "filename": "163_",
      "from": "info@pmaconference.com",
      "x-from": "The Power Marketing Association"
   },
   {
      "Foldername": "junk_file",
      "filename": "165_",
      "from": "gasmart@gasmart.com",
      "x-from": "Gasmart@Gasmart.com"
   },
   {
      "Foldername": "junk_file",
      "filename": "166_",
      "from": "events@eyefoenergy.com",
      "x-from": "Eyeforenergy"
   },
   {
      "Foldername": "junk_file",
      "filename": "167_",
      "from": "j.jill@service.jjill.com",
      "x-from": "J.Jill"
   },
   {
      "Foldername": "junk_file",
      "filename": "168_",
      "from": "announcements.ets@enron.com",
      "x-from": "ETS General Announcements"
   },
   {
      "Foldername": "junk_file",
      "filename": "169_",
      "from": "mark.mcconnell@enron.com",
      "x-from": "McConnell, Mark"
   },
   {
      "Foldername": "junk_file",
      "filename": "16_",
      "from": "angela.white@enron.com",
      "x-from": "White, Angela"
   },
   {
      "Foldername": "junk_file",
      "filename": "170_",
      "from": "announcements.enron@enron.com",
      "x-from": "Enron General Announcements"
   },
   {
      "Foldername": "junk_file",
      "filename": "171_",
      "from": "mark.mcconnell@enron.com",
      "x-from": "McConnell, Mark"
   },
   {
      "Foldername": "junk_file",
      "filename": "172_",
      "from": "elizabeth.brown@enron.com",
      "x-from": "Brown, Elizabeth"
   },
   {
      "Foldername": "junk_file",
      "filename": "173_",
      "from": "fhelme@avaya.com",
      "x-from": "Helme, Melinda M (Flo)"
   },
   {
      "Foldername": "junk_file",
      "filename": "174_",
      "from": "michael.bodnar@enron.com",
      "x-from": "Bodnar, Michael"
   },
   {
      "Foldername": "junk_file",
      "filename": "175_",
      "from": "jan.moore@enron.com",
      "x-from": "Moore, Jan"
   },
   {
      "Foldername": "junk_file",
      "filename": "176_",
      "from": "michelle.lokay@enron.com",
      "x-from": "Lokay, Michelle"
   },
   {
      "Foldername": "junk_file",
      "filename": "177_",
      "from": "elizabeth.brown@enron.com",
      "x-from": "Brown, Elizabeth"
   },
   {
      "Foldername": "junk_file",
      "filename": "178_",
      "from": "mansoor.abdmoulaie@enron.com",
      "x-from": "Abdmoulaie, Mansoor"
   },
   {
      "Foldername": "junk_file",
      "filename": "179_",
      "from": "mark.mcconnell@enron.com",
      "x-from": "McConnell, Mark"
   },
   {
      "Foldername": "junk_file",
      "filename": "17_",
      "from": "michael.bodnar@enron.com",
      "x-from": "Bodnar, Michael"
   },
   {
      "Foldername": "junk_file",
      "filename": "180_",
      "from": "elizabeth.brown@enron.com",
      "x-from": "Brown, Elizabeth"
   },
   {
      "Foldername": "junk_file",
      "filename": "182_",
      "from": "newsletter@rigzone.com",
      "x-from": "newsletter@rigzone.com"
   },
   {
      "Foldername": "junk_file",
      "filename": "183_",
      "from": "10182829@mbox.surecom.com",
      "x-from": "Energy Argus"
   },
   {
      "Foldername": "junk_file",
      "filename": "185_",
      "from": "teb.lokey@enron.com",
      "x-from": "Lokey, Teb"
   },
   {
      "Foldername": "junk_file",
      "filename": "186_",
      "from": "chairman.ets@enron.com",
      "x-from": "ETS Office of the Chairman"
   },
   {
      "Foldername": "junk_file",
      "filename": "187_",
      "from": "linda.wehring@dynegy.com",
      "x-from": "Linda.Wehring@dynegy.com"
   },
   {
      "Foldername": "junk_file",
      "filename": "188_",
      "from": "announcements.enron@enron.com",
      "x-from": "Enron General Announcements"
   },
   {
      "Foldername": "junk_file",
      "filename": "18_",
      "from": "steven.harris@enron.com",
      "x-from": "Harris, Steven"
   },
   {
      "Foldername": "junk_file",
      "filename": "190_",
      "from": "lippmanc@aol.com",
      "x-from": "Lippmanc@aol.com"
   },
   {
      "Foldername": "junk_file",
      "filename": "191_",
      "from": "info@pmaconference.com",
      "x-from": "The Power Marketing Association"
   },
   {
      "Foldername": "junk_file",
      "filename": "192_",
      "from": "newsletter@rigzone.com",
      "x-from": "newsletter@rigzone.com"
   },
   {
      "Foldername": "junk_file",
      "filename": "195_",
      "from": "newsletter@rigzone.com",
      "x-from": "newsletter@rigzone.com"
   },
   {
      "Foldername": "junk_file",
      "filename": "196_",
      "from": "ben.asante@enron.com",
      "x-from": "Asante, Ben"
   },
   {
      "Foldername": "junk_file",
      "filename": "197_",
      "from": "center.ets@enron.com",
      "x-from": "ETS Solution Center"
   },
   {
      "Foldername": "junk_file",
      "filename": "198_",
      "from": "a..howard@enron.com",
      "x-from": "Howard, Kevin A."
   },
   {
      "Foldername": "junk_file",
      "filename": "199_",
      "from": "steven.harris@enron.com",
      "x-from": "Harris, Steven"
   },
   {
      "Foldername": "junk_file",
      "filename": "19_",
      "from": "angela.white@enron.com",
      "x-from": "White, Angela"
   },
   {
      "Foldername": "junk_file",
      "filename": "1_",
      "from": "newsletter@rigzone.com",
      "x-from": "newsletter@rigzone.com"
   },
   {
      "Foldername": "junk_file",
      "filename": "200_",
      "from": "announcements.enron@enron.com",
      "x-from": "Enron General Announcements"
   },
   {
      "Foldername": "junk_file",
      "filename": "201_",
      "from": "chairman.ets@enron.com",
      "x-from": "ETS Office of the Chairman"
   },
   {
      "Foldername": "junk_file",
      "filename": "203_",
      "from": "newsletter@rigzone.com",
      "x-from": "newsletter@rigzone.com"
   },
   {
      "Foldername": "junk_file",
      "filename": "205_",
      "from": "info@energyclasses.com",
      "x-from": "Power Marketers"
   },
   {
      "Foldername": "junk_file",
      "filename": "206_",
      "from": "michael.ratner@enron.com",
      "x-from": "Ratner, Michael"
   },
   {
      "Foldername": "junk_file",
      "filename": "207_",
      "from": "a..howard@enron.com",
      "x-from": "Howard, Kevin A."
   },
   {
      "Foldername": "junk_file",
      "filename": "208_",
      "from": "michael.ratner@enron.com",
      "x-from": "Ratner, Michael"
   },
   {
      "Foldername": "junk_file",
      "filename": "209_",
      "from": "michael.ratner@enron.com",
      "x-from": "Ratner, Michael"
   },
   {
      "Foldername": "junk_file",
      "filename": "20_",
      "from": "michael.bodnar@enron.com",
      "x-from": "Bodnar, Michael"
   },
   {
      "Foldername": "junk_file",
      "filename": "210_",
      "from": "announcements.egs@enron.com",
      "x-from": "EGS General Announcements"
   },
   {
      "Foldername": "junk_file",
      "filename": "211_",
      "from": "steven.harris@enron.com",
      "x-from": "Harris, Steven"
   },
   {
      "Foldername": "junk_file",
      "filename": "212_",
      "from": "steven.harris@enron.com",
      "x-from": "Harris, Steven"
   },
   {
      "Foldername": "junk_file",
      "filename": "213_",
      "from": "jan.moore@enron.com",
      "x-from": "Moore, Jan"
   },
   {
      "Foldername": "junk_file",
      "filename": "214_",
      "from": "audrey.robertson@enron.com",
      "x-from": "Robertson, Audrey"
   },
   {
      "Foldername": "junk_file",
      "filename": "215_",
      "from": "steven.harris@enron.com",
      "x-from": "Harris, Steven"
   },
   {
      "Foldername": "junk_file",
      "filename": "216_",
      "from": "paul.y'barbo@enron.com",
      "x-from": "Y'barbo, Paul"
   },
   {
      "Foldername": "junk_file",
      "filename": "217_",
      "from": "lippmanc@aol.com",
      "x-from": "Lippmanc@aol.com"
   },
   {
      "Foldername": "junk_file",
      "filename": "218_",
      "from": "michelle.lokay@enron.com",
      "x-from": "Lokay, Michelle"
   },
   {
      "Foldername": "junk_file",
      "filename": "219_",
      "from": "newsletter@rigzone.com",
      "x-from": "newsletter@rigzone.com"
   },
   {
      "Foldername": "junk_file",
      "filename": "21_",
      "from": "fhelme@avaya.com",
      "x-from": "Helme, Melinda M (Flo)"
   },
   {
      "Foldername": "junk_file",
      "filename": "220_",
      "from": "info@pmaconference.com",
      "x-from": "The Power Marketing Association"
   },
   {
      "Foldername": "junk_file",
      "filename": "222_",
      "from": "j.jill@service.jjill.com",
      "x-from": "J.Jill"
   },
   {
      "Foldername": "junk_file",
      "filename": "223_",
      "from": "elizabeth.brown@enron.com",
      "x-from": "Brown, Elizabeth"
   },
   {
      "Foldername": "junk_file",
      "filename": "224_",
      "from": "info@pmaconference.com",
      "x-from": "Power Marketers"
   },
   {
      "Foldername": "junk_file",
      "filename": "225_",
      "from": "audrey.robertson@enron.com",
      "x-from": "Robertson, Audrey"
   },
   {
      "Foldername": "junk_file",
      "filename": "226_",
      "from": "paul.cherry@enron.com",
      "x-from": "Cherry, Paul"
   },
   {
      "Foldername": "junk_file",
      "filename": "227_",
      "from": "dennis.lee@enron.com",
      "x-from": "Lee, Dennis"
   },
   {
      "Foldername": "junk_file",
      "filename": "228_",
      "from": "info@pmaconference.com",
      "x-from": "The Power Marketing Association"
   },
   {
      "Foldername": "junk_file",
      "filename": "229_",
      "from": "newsletter@rigzone.com",
      "x-from": "newsletter@rigzone.com"
   },
   {
      "Foldername": "junk_file",
      "filename": "22_",
      "from": "paul.cherry@enron.com",
      "x-from": "Cherry, Paul"
   },
   {
      "Foldername": "junk_file",
      "filename": "231_",
      "from": "audrey.robertson@enron.com",
      "x-from": "Robertson, Audrey"
   },
   {
      "Foldername": "junk_file",
      "filename": "232_",
      "from": "announcements.egs@enron.com",
      "x-from": "EGS General Announcements"
   },
   {
      "Foldername": "junk_file",
      "filename": "233_",
      "from": "michael.ratner@enron.com",
      "x-from": "Ratner, Michael"
   },
   {
      "Foldername": "junk_file",
      "filename": "234_",
      "from": "michael.ratner@enron.com",
      "x-from": "Ratner, Michael"
   },
   {
      "Foldername": "junk_file",
      "filename": "235_",
      "from": "michael.ratner@enron.com",
      "x-from": "Ratner, Michael"
   },
   {
      "Foldername": "junk_file",
      "filename": "236_",
      "from": "michael.ratner@enron.com",
      "x-from": "Ratner, Michael"
   },
   {
      "Foldername": "junk_file",
      "filename": "237_",
      "from": "michael.ratner@enron.com",
      "x-from": "Ratner, Michael"
   },
   {
      "Foldername": "junk_file",
      "filename": "238_",
      "from": "audrey.robertson@enron.com",
      "x-from": "Robertson, Audrey"
   },
   {
      "Foldername": "junk_file",
      "filename": "239_",
      "from": "announcements.enron@enron.com",
      "x-from": "Enron General Announcements"
   },
   {
      "Foldername": "junk_file",
      "filename": "23_",
      "from": "michael.bodnar@enron.com",
      "x-from": "Bodnar, Michael"
   },
   {
      "Foldername": "junk_file",
      "filename": "240_",
      "from": "kimberly.watson@enron.com",
      "x-from": "Watson, Kimberly"
   },
   {
      "Foldername": "junk_file",
      "filename": "241_",
      "from": "steven.harris@enron.com",
      "x-from": "Harris, Steven"
   },
   {
      "Foldername": "junk_file",
      "filename": "242_",
      "from": "jan.moore@enron.com",
      "x-from": "Moore, Jan"
   },
   {
      "Foldername": "junk_file",
      "filename": "243_",
      "from": "lorraine.lindberg@enron.com",
      "x-from": "Lindberg, Lorraine"
   },
   {
      "Foldername": "junk_file",
      "filename": "244_",
      "from": "davis.thames@enron.com",
      "x-from": "Thames, Davis"
   },
   {
      "Foldername": "junk_file",
      "filename": "245_",
      "from": "announcements.enron@enron.com",
      "x-from": "Enron General Announcements"
   },
   {
      "Foldername": "junk_file",
      "filename": "246_",
      "from": "rod.hayslett@enron.com",
      "x-from": "Hayslett, Rod"
   },
   {
      "Foldername": "junk_file",
      "filename": "247_",
      "from": "a..howard@enron.com",
      "x-from": "Howard, Kevin A."
   },
   {
      "Foldername": "junk_file",
      "filename": "248_",
      "from": "lippmanc@aol.com",
      "x-from": "Lippmanc@aol.com"
   },
   {
      "Foldername": "junk_file",
      "filename": "249_",
      "from": "announcements.enron@enron.com",
      "x-from": "Enron General Announcements"
   },
   {
      "Foldername": "junk_file",
      "filename": "24_",
      "from": "michelle.lokay@enron.com",
      "x-from": "Lokay, Michelle"
   },
   {
      "Foldername": "junk_file",
      "filename": "250_",
      "from": "michelle.lokay@enron.com",
      "x-from": "Lokay, Michelle"
   },
   {
      "Foldername": "junk_file",
      "filename": "251_",
      "from": "newsletter@rigzone.com",
      "x-from": "newsletter@rigzone.com"
   },
   {
      "Foldername": "junk_file",
      "filename": "252_",
      "from": "tracy.geaccone@enron.com",
      "x-from": "Geaccone, Tracy"
   },
   {
      "Foldername": "junk_file",
      "filename": "253_",
      "from": "jan.moore@enron.com",
      "x-from": "Moore, Jan"
   },
   {
      "Foldername": "junk_file",
      "filename": "254_",
      "from": "julie.armstrong@enron.com",
      "x-from": "Armstrong, Julie"
   },
   {
      "Foldername": "junk_file",
      "filename": "255_",
      "from": "rod.hayslett@enron.com",
      "x-from": "Hayslett, Rod"
   },
   {
      "Foldername": "junk_file",
      "filename": "256_",
      "from": "james.centilli@enron.com",
      "x-from": "Centilli, James"
   },
   {
      "Foldername": "junk_file",
      "filename": "257_",
      "from": "julie.armstrong@enron.com",
      "x-from": "Armstrong, Julie"
   },
   {
      "Foldername": "junk_file",
      "filename": "258_",
      "from": "jan.moore@enron.com",
      "x-from": "Moore, Jan"
   },
   {
      "Foldername": "junk_file",
      "filename": "259_",
      "from": "teb.lokey@enron.com",
      "x-from": "Lokey, Teb"
   },
   {
      "Foldername": "junk_file",
      "filename": "25_",
      "from": "dennis.lee@enron.com",
      "x-from": "Lee, Dennis"
   },
   {
      "Foldername": "junk_file",
      "filename": "260_",
      "from": "jan.moore@enron.com",
      "x-from": "Moore, Jan"
   },
   {
      "Foldername": "junk_file",
      "filename": "261_",
      "from": "bill.rapp@enron.com",
      "x-from": "Rapp, Bill"
   },
   {
      "Foldername": "junk_file",
      "filename": "262_",
      "from": "jan.moore@enron.com",
      "x-from": "Moore, Jan"
   },
   {
      "Foldername": "junk_file",
      "filename": "263_",
      "from": "jan.moore@enron.com",
      "x-from": "Moore, Jan"
   },
   {
      "Foldername": "junk_file",
      "filename": "264_",
      "from": "jan.moore@enron.com",
      "x-from": "Moore, Jan"
   },
   {
      "Foldername": "junk_file",
      "filename": "265_",
      "from": "a..howard@enron.com",
      "x-from": "Howard, Kevin A."
   },
   {
      "Foldername": "junk_file",
      "filename": "266_",
      "from": "rod.hayslett@enron.com",
      "x-from": "Hayslett, Rod"
   },
   {
      "Foldername": "junk_file",
      "filename": "267_",
      "from": "a..howard@enron.com",
      "x-from": "Howard, Kevin A."
   },
   {
      "Foldername": "junk_file",
      "filename": "268_",
      "from": "james.centilli@enron.com",
      "x-from": "Centilli, James"
   },
   {
      "Foldername": "junk_file",
      "filename": "269_",
      "from": "jan.moore@enron.com",
      "x-from": "Moore, Jan"
   },
   {
      "Foldername": "junk_file",
      "filename": "26_",
      "from": "newsletter@rigzone.com",
      "x-from": "newsletter@rigzone.com"
   },
   {
      "Foldername": "junk_file",
      "filename": "270_",
      "from": "a..howard@enron.com",
      "x-from": "Howard, Kevin A."
   },
   {
      "Foldername": "junk_file",
      "filename": "271_",
      "from": "rod.hayslett@enron.com",
      "x-from": "Hayslett, Rod"
   },
   {
      "Foldername": "junk_file",
      "filename": "272_",
      "from": "a..howard@enron.com",
      "x-from": "Howard, Kevin A."
   },
   {
      "Foldername": "junk_file",
      "filename": "273_",
      "from": "bruno@eyeforenergy.com",
      "x-from": "Eyeforenergy"
   },
   {
      "Foldername": "junk_file",
      "filename": "274_",
      "from": "newsletter@rigzone.com",
      "x-from": "newsletter@rigzone.com"
   },
   {
      "Foldername": "junk_file",
      "filename": "277_",
      "from": "davis.thames@enron.com",
      "x-from": "Thames, Davis"
   },
   {
      "Foldername": "junk_file",
      "filename": "278_",
      "from": "deanrogers@energyclasses.com",
      "x-from": "Kase and Company, Inc."
   },
   {
      "Foldername": "junk_file",
      "filename": "279_",
      "from": "davis.thames@enron.com",
      "x-from": "Thames, Davis"
   },
   {
      "Foldername": "junk_file",
      "filename": "27_",
      "from": "jan.moore@enron.com",
      "x-from": "Moore, Jan"
   },
   {
      "Foldername": "junk_file",
      "filename": "280_",
      "from": "jeanne.licciardo@enron.com",
      "x-from": "Licciardo, Jeanne"
   },
   {
      "Foldername": "junk_file",
      "filename": "281_",
      "from": "a..howard@enron.com",
      "x-from": "Howard, Kevin A."
   },
   {
      "Foldername": "junk_file",
      "filename": "282_",
      "from": "linda.trevino@enron.com",
      "x-from": "Trevino, Linda"
   },
   {
      "Foldername": "junk_file",
      "filename": "283_",
      "from": "richard.riehm@enron.com",
      "x-from": "Riehm, Richard"
   },
   {
      "Foldername": "junk_file",
      "filename": "284_",
      "from": "teb.lokey@enron.com",
      "x-from": "Lokey, Teb"
   },
   {
      "Foldername": "junk_file",
      "filename": "285_",
      "from": "glen.hass@enron.com",
      "x-from": "Hass, Glen"
   },
   {
      "Foldername": "junk_file",
      "filename": "286_",
      "from": "tk.lohman@enron.com",
      "x-from": "Lohman, TK"
   },
   {
      "Foldername": "junk_file",
      "filename": "287_",
      "from": "glen.hass@enron.com",
      "x-from": "Hass, Glen"
   },
   {
      "Foldername": "junk_file",
      "filename": "288_",
      "from": "elizabeth.brown@enron.com",
      "x-from": "Brown, Elizabeth"
   },
   {
      "Foldername": "junk_file",
      "filename": "289_",
      "from": "glen.hass@enron.com",
      "x-from": "Hass, Glen"
   },
   {
      "Foldername": "junk_file",
      "filename": "28_",
      "from": "steven.harris@enron.com",
      "x-from": "Harris, Steven"
   },
   {
      "Foldername": "junk_file",
      "filename": "290_",
      "from": "newsletter@rigzone.com",
      "x-from": "newsletter@rigzone.com"
   },
   {
      "Foldername": "junk_file",
      "filename": "292_",
      "from": "newsletter@rigzone.com",
      "x-from": "newsletter@rigzone.com"
   },
   {
      "Foldername": "junk_file",
      "filename": "294_",
      "from": "center.ets@enron.com",
      "x-from": "ETS Solution Center"
   },
   {
      "Foldername": "junk_file",
      "filename": "295_",
      "from": "john@pgsenergy.com",
      "x-from": "John Adamiak"
   },
   {
      "Foldername": "junk_file",
      "filename": "297_",
      "from": "newsletter@rigzone.com",
      "x-from": "newsletter@rigzone.com"
   },
   {
      "Foldername": "junk_file",
      "filename": "298_",
      "from": "aherbst@utilisenergy.com",
      "x-from": "Utilis Energy"
   },
   {
      "Foldername": "junk_file",
      "filename": "29_",
      "from": "newsletter@rigzone.com",
      "x-from": "newsletter@rigzone.com"
   },
   {
      "Foldername": "junk_file",
      "filename": "2_",
      "from": "enerfaxdaily@enerfax.com",
      "x-from": "enerfaxdaily@enerfax.com"
   },
   {
      "Foldername": "junk_file",
      "filename": "300_",
      "from": "info@pmaconference.com",
      "x-from": "The Power Marketing Association"
   },
   {
      "Foldername": "junk_file",
      "filename": "301_",
      "from": "newsletter@rigzone.com",
      "x-from": "newsletter@rigzone.com"
   },
   {
      "Foldername": "junk_file",
      "filename": "302_",
      "from": "enerfaxdaily@enerfax.com",
      "x-from": "enerfaxdaily@enerfax.com"
   },
   {
      "Foldername": "junk_file",
      "filename": "303_",
      "from": "lynn.blair@enron.com",
      "x-from": "Blair, Lynn"
   },
   {
      "Foldername": "junk_file",
      "filename": "304_",
      "from": "info@energyclasses.com",
      "x-from": "Power Marketers"
   },
   {
      "Foldername": "junk_file",
      "filename": "305_",
      "from": "terri.bachand@enron.com",
      "x-from": "Bachand, Terri"
   },
   {
      "Foldername": "junk_file",
      "filename": "306_",
      "from": "a..howard@enron.com",
      "x-from": "Howard, Kevin A."
   },
   {
      "Foldername": "junk_file",
      "filename": "307_",
      "from": "tracy.geaccone@enron.com",
      "x-from": "Geaccone, Tracy"
   },
   {
      "Foldername": "junk_file",
      "filename": "308_",
      "from": "tracy.scott@enron.com",
      "x-from": "Scott, Tracy"
   },
   {
      "Foldername": "junk_file",
      "filename": "309_",
      "from": "announcements.enron@enron.com",
      "x-from": "Enron General Announcements"
   },
   {
      "Foldername": "junk_file",
      "filename": "310_",
      "from": "info@pmaconference.com",
      "x-from": "The Power Marketing Association"
   },
   {
      "Foldername": "junk_file",
      "filename": "311_",
      "from": "info@pmaconference.com",
      "x-from": "The Power Marketing Association"
   },
   {
      "Foldername": "junk_file",
      "filename": "312_",
      "from": "newsletter@rigzone.com",
      "x-from": "newsletter@rigzone.com"
   },
   {
      "Foldername": "junk_file",
      "filename": "313_",
      "from": "talbots@clickaction.net",
      "x-from": "talbots.com"
   },
   {
      "Foldername": "junk_file",
      "filename": "315_",
      "from": "bert.hernandez@enron.com",
      "x-from": "Hernandez, Bert"
   },
   {
      "Foldername": "junk_file",
      "filename": "316_",
      "from": "center.ets@enron.com",
      "x-from": "ETS Solution Center"
   },
   {
      "Foldername": "junk_file",
      "filename": "317_",
      "from": "bruno@eyeforenergy.com",
      "x-from": "Eyeforenergy"
   },
   {
      "Foldername": "junk_file",
      "filename": "318_",
      "from": "center.ets@enron.com",
      "x-from": "ETS Solution Center"
   },
   {
      "Foldername": "junk_file",
      "filename": "319_",
      "from": "jan.moore@enron.com",
      "x-from": "Moore, Jan"
   },
   {
      "Foldername": "junk_file",
      "filename": "31_",
      "from": "announcements.enron@enron.com",
      "x-from": "Enron General Announcements"
   },
   {
      "Foldername": "junk_file",
      "filename": "320_",
      "from": "a..howard@enron.com",
      "x-from": "Howard, Kevin A."
   },
   {
      "Foldername": "junk_file",
      "filename": "321_",
      "from": "lorraine.lindberg@enron.com",
      "x-from": "Lindberg, Lorraine"
   },
   {
      "Foldername": "junk_file",
      "filename": "322_",
      "from": "dennis.lee@enron.com",
      "x-from": "Lee, Dennis"
   },
   {
      "Foldername": "junk_file",
      "filename": "323_",
      "from": "rod.hayslett@enron.com",
      "x-from": "Hayslett, Rod"
   },
   {
      "Foldername": "junk_file",
      "filename": "325_",
      "from": "newsletter@rigzone.com",
      "x-from": "newsletter@rigzone.com"
   },
   {
      "Foldername": "junk_file",
      "filename": "327_",
      "from": "management.ets@enron.com",
      "x-from": "ETS Information Risk Management"
   },
   {
      "Foldername": "junk_file",
      "filename": "328_",
      "from": "fran.fagan@enron.com",
      "x-from": "Fagan, Fran"
   },
   {
      "Foldername": "junk_file",
      "filename": "329_",
      "from": "a..howard@enron.com",
      "x-from": "Howard, Kevin A."
   },
   {
      "Foldername": "junk_file",
      "filename": "32_",
      "from": "lhinson@allianceworldwide.com",
      "x-from": "Lee Ann Hinson"
   },
   {
      "Foldername": "junk_file",
      "filename": "330_",
      "from": "a..howard@enron.com",
      "x-from": "Howard, Kevin A."
   },
   {
      "Foldername": "junk_file",
      "filename": "331_",
      "from": "rod.hayslett@enron.com",
      "x-from": "Hayslett, Rod"
   },
   {
      "Foldername": "junk_file",
      "filename": "332_",
      "from": "rod.hayslett@enron.com",
      "x-from": "Hayslett, Rod"
   },
   {
      "Foldername": "junk_file",
      "filename": "333_",
      "from": "michael.ratner@enron.com",
      "x-from": "Ratner, Michael"
   },
   {
      "Foldername": "junk_file",
      "filename": "334_",
      "from": "audrey.robertson@enron.com",
      "x-from": "Robertson, Audrey"
   },
   {
      "Foldername": "junk_file",
      "filename": "335_",
      "from": "tracy.geaccone@enron.com",
      "x-from": "Geaccone, Tracy"
   },
   {
      "Foldername": "junk_file",
      "filename": "336_",
      "from": "tracy.geaccone@enron.com",
      "x-from": "Geaccone, Tracy"
   },
   {
      "Foldername": "junk_file",
      "filename": "337_",
      "from": "dennis.lee@enron.com",
      "x-from": "Lee, Dennis"
   },
   {
      "Foldername": "junk_file",
      "filename": "338_",
      "from": "angela.white@enron.com",
      "x-from": "White, Angela"
   },
   {
      "Foldername": "junk_file",
      "filename": "339_",
      "from": "events@skippingstone.com",
      "x-from": "events@skippingstone.com"
   },
   {
      "Foldername": "junk_file",
      "filename": "340_",
      "from": "info@pmaconference.com",
      "x-from": "The Power Marketing Association"
   },
   {
      "Foldername": "junk_file",
      "filename": "341_",
      "from": "newsletter@rigzone.com",
      "x-from": "newsletter@rigzone.com"
   },
   {
      "Foldername": "junk_file",
      "filename": "342_",
      "from": "j.jill@service.jjill.com",
      "x-from": "J.Jill"
   },
   {
      "Foldername": "junk_file",
      "filename": "343_",
      "from": "center.ets@enron.com",
      "x-from": "ETS Solution Center"
   },
   {
      "Foldername": "junk_file",
      "filename": "344_",
      "from": "audrey.robertson@enron.com",
      "x-from": "Robertson, Audrey"
   },
   {
      "Foldername": "junk_file",
      "filename": "345_",
      "from": "dennis.lee@enron.com",
      "x-from": "Lee, Dennis"
   },
   {
      "Foldername": "junk_file",
      "filename": "346_",
      "from": "dennis.lee@enron.com",
      "x-from": "Lee, Dennis"
   },
   {
      "Foldername": "junk_file",
      "filename": "347_",
      "from": "deanrogers@energyclasses.com",
      "x-from": "Dean Rogers"
   },
   {
      "Foldername": "junk_file",
      "filename": "348_",
      "from": "angela.white@enron.com",
      "x-from": "White, Angela"
   },
   {
      "Foldername": "junk_file",
      "filename": "349_",
      "from": "angela.white@enron.com",
      "x-from": "White, Angela"
   },
   {
      "Foldername": "junk_file",
      "filename": "34_",
      "from": "adamsholly@netscape.net",
      "x-from": "holly adams"
   },
   {
      "Foldername": "junk_file",
      "filename": "350_",
      "from": "dennis.lee@enron.com",
      "x-from": "Lee, Dennis"
   },
   {
      "Foldername": "junk_file",
      "filename": "351_",
      "from": "dennis.lee@enron.com",
      "x-from": "Lee, Dennis"
   },
   {
      "Foldername": "junk_file",
      "filename": "352_",
      "from": "john@pgsenergy.com",
      "x-from": "John Adamiak"
   },
   {
      "Foldername": "junk_file",
      "filename": "353_",
      "from": "audrey.robertson@enron.com",
      "x-from": "Robertson, Audrey"
   },
   {
      "Foldername": "junk_file",
      "filename": "354_",
      "from": "newsletter@rigzone.com",
      "x-from": "newsletter@rigzone.com"
   },
   {
      "Foldername": "junk_file",
      "filename": "357_",
      "from": "jeanette.doll@enron.com",
      "x-from": "Doll, Jeanette"
   },
   {
      "Foldername": "junk_file",
      "filename": "358_",
      "from": "eric.gadd@enron.com",
      "x-from": "Gadd, Eric"
   },
   {
      "Foldername": "junk_file",
      "filename": "359_",
      "from": "steven.harris@enron.com",
      "x-from": "Harris, Steven"
   },
   {
      "Foldername": "junk_file",
      "filename": "35_",
      "from": "maria.pavlou@enron.com",
      "x-from": "Pavlou, Maria"
   },
   {
      "Foldername": "junk_file",
      "filename": "360_",
      "from": "james.centilli@enron.com",
      "x-from": "Centilli, James"
   },
   {
      "Foldername": "junk_file",
      "filename": "361_",
      "from": "steven.harris@enron.com",
      "x-from": "Harris, Steven"
   },
   {
      "Foldername": "junk_file",
      "filename": "362_",
      "from": "audrey.robertson@enron.com",
      "x-from": "Robertson, Audrey"
   },
   {
      "Foldername": "junk_file",
      "filename": "363_",
      "from": "steven.harris@enron.com",
      "x-from": "Harris, Steven"
   },
   {
      "Foldername": "junk_file",
      "filename": "364_",
      "from": "fran.fagan@enron.com",
      "x-from": "Fagan, Fran"
   },
   {
      "Foldername": "junk_file",
      "filename": "365_",
      "from": "angela.white@enron.com",
      "x-from": "White, Angela"
   },
   {
      "Foldername": "junk_file",
      "filename": "366_",
      "from": "fran.fagan@enron.com",
      "x-from": "Fagan, Fran"
   },
   {
      "Foldername": "junk_file",
      "filename": "367_",
      "from": "elizabeth.brown@enron.com",
      "x-from": "Brown, Elizabeth"
   },
   {
      "Foldername": "junk_file",
      "filename": "368_",
      "from": "angela.white@enron.com",
      "x-from": "White, Angela"
   },
   {
      "Foldername": "junk_file",
      "filename": "369_",
      "from": "jan.moore@enron.com",
      "x-from": "Moore, Jan"
   },
   {
      "Foldername": "junk_file",
      "filename": "36_",
      "from": "maria.pavlou@enron.com",
      "x-from": "Pavlou, Maria"
   },
   {
      "Foldername": "junk_file",
      "filename": "370_",
      "from": "gina.taylor@enron.com",
      "x-from": "Taylor, Gina"
   },
   {
      "Foldername": "junk_file",
      "filename": "371_",
      "from": "gina.taylor@enron.com",
      "x-from": "Taylor, Gina"
   },
   {
      "Foldername": "junk_file",
      "filename": "372_",
      "from": "gina.taylor@enron.com",
      "x-from": "Taylor, Gina"
   },
   {
      "Foldername": "junk_file",
      "filename": "373_",
      "from": "dennis.lee@enron.com",
      "x-from": "Lee, Dennis"
   },
   {
      "Foldername": "junk_file",
      "filename": "374_",
      "from": "anitha.mathis@enron.com",
      "x-from": "Mathis, Anitha"
   },
   {
      "Foldername": "junk_file",
      "filename": "375_",
      "from": "dennis.lee@enron.com",
      "x-from": "Lee, Dennis"
   },
   {
      "Foldername": "junk_file",
      "filename": "376_",
      "from": "newsletter@rigzone.com",
      "x-from": "newsletter@rigzone.com"
   },
   {
      "Foldername": "junk_file",
      "filename": "379_",
      "from": "announcements.egs@enron.com",
      "x-from": "EGS General Announcements"
   },
   {
      "Foldername": "junk_file",
      "filename": "37_",
      "from": "lorna.brennan@enron.com",
      "x-from": "Brennan, Lorna"
   },
   {
      "Foldername": "junk_file",
      "filename": "380_",
      "from": "adamsholly@netscape.net",
      "x-from": "holly adams"
   },
   {
      "Foldername": "junk_file",
      "filename": "381_",
      "from": "tracy.geaccone@enron.com",
      "x-from": "Geaccone, Tracy"
   },
   {
      "Foldername": "junk_file",
      "filename": "382_",
      "from": "tracy.geaccone@enron.com",
      "x-from": "Geaccone, Tracy"
   },
   {
      "Foldername": "junk_file",
      "filename": "383_",
      "from": "tracy.geaccone@enron.com",
      "x-from": "Geaccone, Tracy"
   },
   {
      "Foldername": "junk_file",
      "filename": "384_",
      "from": "a..howard@enron.com",
      "x-from": "Howard, Kevin A."
   },
   {
      "Foldername": "junk_file",
      "filename": "386_",
      "from": "linda.trevino@enron.com",
      "x-from": "Trevino, Linda"
   },
   {
      "Foldername": "junk_file",
      "filename": "387_",
      "from": "michelle.lokay@enron.com",
      "x-from": "Lokay, Michelle"
   },
   {
      "Foldername": "junk_file",
      "filename": "388_",
      "from": "a..howard@enron.com",
      "x-from": "Howard, Kevin A."
   },
   {
      "Foldername": "junk_file",
      "filename": "389_",
      "from": "bob.chandler@enron.com",
      "x-from": "Chandler, Bob"
   },
   {
      "Foldername": "junk_file",
      "filename": "38_",
      "from": "chairman.enron@enron.com",
      "x-from": "Enron Office Of The Chairman"
   },
   {
      "Foldername": "junk_file",
      "filename": "390_",
      "from": "adamsholly@netscape.net",
      "x-from": "holly adams"
   },
   {
      "Foldername": "junk_file",
      "filename": "391_",
      "from": "ron.matthews@enron.com",
      "x-from": "Matthews, Ron"
   },
   {
      "Foldername": "junk_file",
      "filename": "392_",
      "from": "angela.white@enron.com",
      "x-from": "White, Angela"
   },
   {
      "Foldername": "junk_file",
      "filename": "393_",
      "from": "newsletter@rigzone.com",
      "x-from": "newsletter@rigzone.com"
   },
   {
      "Foldername": "junk_file",
      "filename": "394_",
      "from": "deanrogers@energyclasses.com",
      "x-from": "Kase & Co."
   },
   {
      "Foldername": "junk_file",
      "filename": "397_",
      "from": "newsletter@rigzone.com",
      "x-from": "newsletter@rigzone.com"
   },
   {
      "Foldername": "junk_file",
      "filename": "399_",
      "from": "bruno@eyeforenergy.com",
      "x-from": "Eyeforenergy"
   },
   {
      "Foldername": "junk_file",
      "filename": "39_",
      "from": "jan.moore@enron.com",
      "x-from": "Moore, Jan"
   },
   {
      "Foldername": "junk_file",
      "filename": "3_",
      "from": "audrey.robertson@enron.com",
      "x-from": "Robertson, Audrey"
   },
   {
      "Foldername": "junk_file",
      "filename": "400_",
      "from": "audrey.robertson@enron.com",
      "x-from": "Robertson, Audrey"
   },
   {
      "Foldername": "junk_file",
      "filename": "401_",
      "from": "info@pmaconference.com",
      "x-from": "The Power Marketing Association"
   },
   {
      "Foldername": "junk_file",
      "filename": "402_",
      "from": "newsletter@rigzone.com",
      "x-from": "newsletter@rigzone.com"
   },
   {
      "Foldername": "junk_file",
      "filename": "404_",
      "from": "announcements.enron@enron.com",
      "x-from": "Enron General Announcements"
   },
   {
      "Foldername": "junk_file",
      "filename": "405_",
      "from": "announcements.enron@enron.com",
      "x-from": "Enron General Announcements"
   },
   {
      "Foldername": "junk_file",
      "filename": "406_",
      "from": "info@pmaconference.com",
      "x-from": "The Power Marketing Association"
   },
   {
      "Foldername": "junk_file",
      "filename": "407_",
      "from": "ramona.betancourt@enron.com",
      "x-from": "Betancourt, Ramona"
   },
   {
      "Foldername": "junk_file",
      "filename": "408_",
      "from": "john.buchanan@enron.com",
      "x-from": "Buchanan, John"
   },
   {
      "Foldername": "junk_file",
      "filename": "409_",
      "from": "glen.hass@enron.com",
      "x-from": "Hass, Glen"
   },
   {
      "Foldername": "junk_file",
      "filename": "40_",
      "from": "newsletter@rigzone.com",
      "x-from": "newsletter@rigzone.com"
   },
   {
      "Foldername": "junk_file",
      "filename": "410_",
      "from": "kimberly.watson@enron.com",
      "x-from": "Watson, Kimberly"
   },
   {
      "Foldername": "junk_file",
      "filename": "411_",
      "from": "a..howard@enron.com",
      "x-from": "Howard, Kevin A."
   },
   {
      "Foldername": "junk_file",
      "filename": "412_",
      "from": "a..howard@enron.com",
      "x-from": "Howard, Kevin A."
   },
   {
      "Foldername": "junk_file",
      "filename": "413_",
      "from": "jeanette.doll@enron.com",
      "x-from": "Doll, Jeanette"
   },
   {
      "Foldername": "junk_file",
      "filename": "414_",
      "from": "jeanette.doll@enron.com",
      "x-from": "Doll, Jeanette"
   },
   {
      "Foldername": "junk_file",
      "filename": "415_",
      "from": "john.buchanan@enron.com",
      "x-from": "Buchanan, John"
   },
   {
      "Foldername": "junk_file",
      "filename": "416_",
      "from": "audrey.robertson@enron.com",
      "x-from": "Robertson, Audrey"
   },
   {
      "Foldername": "junk_file",
      "filename": "417_",
      "from": "communications@enron.com",
      "x-from": "Communications"
   },
   {
      "Foldername": "junk_file",
      "filename": "418_",
      "from": "ramona.betancourt@enron.com",
      "x-from": "Betancourt, Ramona"
   },
   {
      "Foldername": "junk_file",
      "filename": "419_",
      "from": "terry.kowalke@enron.com",
      "x-from": "Kowalke, Terry"
   },
   {
      "Foldername": "junk_file",
      "filename": "420_",
      "from": "darrell.schoolcraft@enron.com",
      "x-from": "Schoolcraft, Darrell"
   },
   {
      "Foldername": "junk_file",
      "filename": "421_",
      "from": "notification.isc@enron.com",
      "x-from": "ISC Systems Notification"
   },
   {
      "Foldername": "junk_file",
      "filename": "422_",
      "from": "a..howard@enron.com",
      "x-from": "Howard, Kevin A."
   },
   {
      "Foldername": "junk_file",
      "filename": "423_",
      "from": "announcements.egs@enron.com",
      "x-from": "EGS General Announcements"
   },
   {
      "Foldername": "junk_file",
      "filename": "424_",
      "from": "jan.moore@enron.com",
      "x-from": "Moore, Jan"
   },
   {
      "Foldername": "junk_file",
      "filename": "425_",
      "from": "mark.mcconnell@enron.com",
      "x-from": "McConnell, Mark"
   },
   {
      "Foldername": "junk_file",
      "filename": "428_",
      "from": "center.ets@enron.com",
      "x-from": "ETS Solution Center"
   },
   {
      "Foldername": "junk_file",
      "filename": "429_",
      "from": "kimberly.watson@enron.com",
      "x-from": "Watson, Kimberly"
   },
   {
      "Foldername": "junk_file",
      "filename": "42_",
      "from": "announcements.enron@enron.com",
      "x-from": "Enron General Announcements"
   },
   {
      "Foldername": "junk_file",
      "filename": "430_",
      "from": "tk.lohman@enron.com",
      "x-from": "Lohman, TK"
   },
   {
      "Foldername": "junk_file",
      "filename": "431_",
      "from": "steven.harris@enron.com",
      "x-from": "Harris, Steven"
   },
   {
      "Foldername": "junk_file",
      "filename": "432_",
      "from": "kevin.hyatt@enron.com",
      "x-from": "Hyatt, Kevin"
   },
   {
      "Foldername": "junk_file",
      "filename": "433_",
      "from": "elizabeth.brown@enron.com",
      "x-from": "Brown, Elizabeth"
   },
   {
      "Foldername": "junk_file",
      "filename": "434_",
      "from": "jan.moore@enron.com",
      "x-from": "Moore, Jan"
   },
   {
      "Foldername": "junk_file",
      "filename": "435_",
      "from": "steven.harris@enron.com",
      "x-from": "Harris, Steven"
   },
   {
      "Foldername": "junk_file",
      "filename": "436_",
      "from": "michelle.lokay@enron.com",
      "x-from": "Lokay, Michelle"
   },
   {
      "Foldername": "junk_file",
      "filename": "437_",
      "from": "communications@enron.com",
      "x-from": "Communications"
   },
   {
      "Foldername": "junk_file",
      "filename": "438_",
      "from": "info@pmaconference.com",
      "x-from": "The Power Marketing Association"
   },
   {
      "Foldername": "junk_file",
      "filename": "43_",
      "from": "newsletter@rigzone.com",
      "x-from": "newsletter@rigzone.com"
   },
   {
      "Foldername": "junk_file",
      "filename": "440_",
      "from": "newsletter@rigzone.com",
      "x-from": "newsletter@rigzone.com"
   },
   {
      "Foldername": "junk_file",
      "filename": "441_",
      "from": "executive.office@enron.com",
      "x-from": "Office of the Chief Executive"
   },
   {
      "Foldername": "junk_file",
      "filename": "442_",
      "from": "announcements.enron@enron.com",
      "x-from": "Enron General Announcements"
   },
   {
      "Foldername": "junk_file",
      "filename": "443_",
      "from": "communications@enron.com",
      "x-from": "Communications"
   },
   {
      "Foldername": "junk_file",
      "filename": "444_",
      "from": "talbots@clickaction.net",
      "x-from": "talbots.com"
   },
   {
      "Foldername": "junk_file",
      "filename": "445_",
      "from": "info@pmaconference.com",
      "x-from": "The Power Marketing Association"
   },
   {
      "Foldername": "junk_file",
      "filename": "446_",
      "from": "gasmart@gasmart.com",
      "x-from": "Gasmart@Gasmart.com"
   },
   {
      "Foldername": "junk_file",
      "filename": "447_",
      "from": "glen.hass@enron.com",
      "x-from": "Hass, Glen"
   },
   {
      "Foldername": "junk_file",
      "filename": "448_",
      "from": "anitha.mathis@enron.com",
      "x-from": "Mathis, Anitha"
   },
   {
      "Foldername": "junk_file",
      "filename": "449_",
      "from": "elizabeth.brown@enron.com",
      "x-from": "Brown, Elizabeth"
   },
   {
      "Foldername": "junk_file",
      "filename": "44_",
      "from": "andy.brady@enron.com",
      "x-from": "Brady, Andy"
   },
   {
      "Foldername": "junk_file",
      "filename": "450_",
      "from": "elizabeth.brown@enron.com",
      "x-from": "Brown, Elizabeth"
   },
   {
      "Foldername": "junk_file",
      "filename": "451_",
      "from": "adamsholly@netscape.net",
      "x-from": "holly adams"
   },
   {
      "Foldername": "junk_file",
      "filename": "452_",
      "from": "terri.bachand@enron.com",
      "x-from": "Bachand, Terri"
   },
   {
      "Foldername": "junk_file",
      "filename": "453_",
      "from": "jan.moore@enron.com",
      "x-from": "Moore, Jan"
   },
   {
      "Foldername": "junk_file",
      "filename": "454_",
      "from": "j.jill@service.jjill.com",
      "x-from": "J.Jill"
   },
   {
      "Foldername": "junk_file",
      "filename": "455_",
      "from": "audrey.robertson@enron.com",
      "x-from": "Robertson, Audrey"
   },
   {
      "Foldername": "junk_file",
      "filename": "457_",
      "from": "newsletter@rigzone.com",
      "x-from": "newsletter@rigzone.com"
   },
   {
      "Foldername": "junk_file",
      "filename": "458_",
      "from": "gasmart@gasmart.com",
      "x-from": "Gasmart@Gasmart.com"
   },
   {
      "Foldername": "junk_file",
      "filename": "459_",
      "from": "pma@powermarketers.com",
      "x-from": "Power Markets 2002"
   },
   {
      "Foldername": "junk_file",
      "filename": "45_",
      "from": "glen.hass@enron.com",
      "x-from": "Hass, Glen"
   },
   {
      "Foldername": "junk_file",
      "filename": "460_",
      "from": "audrey.robertson@enron.com",
      "x-from": "Robertson, Audrey"
   },
   {
      "Foldername": "junk_file",
      "filename": "462_",
      "from": "newsletter@rigzone.com",
      "x-from": "newsletter@rigzone.com"
   },
   {
      "Foldername": "junk_file",
      "filename": "463_",
      "from": "info@pmaconference.com",
      "x-from": "The Power Marketing Association"
   },
   {
      "Foldername": "junk_file",
      "filename": "464_",
      "from": "kimberly.watson@enron.com",
      "x-from": "Watson, Kimberly"
   },
   {
      "Foldername": "junk_file",
      "filename": "465_",
      "from": "bill.rapp@enron.com",
      "x-from": "Rapp, Bill"
   },
   {
      "Foldername": "junk_file",
      "filename": "467_",
      "from": "newsletter@rigzone.com",
      "x-from": "newsletter@rigzone.com"
   },
   {
      "Foldername": "junk_file",
      "filename": "468_",
      "from": "executive.office@enron.com",
      "x-from": "Office of the Chief Executive"
   },
   {
      "Foldername": "junk_file",
      "filename": "469_",
      "from": "kimberly.watson@enron.com",
      "x-from": "Watson, Kimberly"
   },
   {
      "Foldername": "junk_file",
      "filename": "46_",
      "from": "audrey.robertson@enron.com",
      "x-from": "Robertson, Audrey"
   },
   {
      "Foldername": "junk_file",
      "filename": "470_",
      "from": "announcements.enron@enron.com",
      "x-from": "Enron General Announcements"
   },
   {
      "Foldername": "junk_file",
      "filename": "471_",
      "from": "chairman.ets@enron.com",
      "x-from": "ETS Office of the Chairman"
   },
   {
      "Foldername": "junk_file",
      "filename": "472_",
      "from": "audrey.robertson@enron.com",
      "x-from": "Robertson, Audrey"
   },
   {
      "Foldername": "junk_file",
      "filename": "473_",
      "from": "john@pgsenergy.com",
      "x-from": "John Adamiak"
   },
   {
      "Foldername": "junk_file",
      "filename": "474_",
      "from": "info@pmaconference.com",
      "x-from": "PGS Energy Training"
   },
   {
      "Foldername": "junk_file",
      "filename": "476_",
      "from": "newsletter@rigzone.com",
      "x-from": "newsletter@rigzone.com"
   },
   {
      "Foldername": "junk_file",
      "filename": "477_",
      "from": "newsletter@rigzone.com",
      "x-from": "newsletter@rigzone.com"
   },
   {
      "Foldername": "junk_file",
      "filename": "479_",
      "from": "audrey.robertson@enron.com",
      "x-from": "Robertson, Audrey"
   },
   {
      "Foldername": "junk_file",
      "filename": "47_",
      "from": "announcements.enron@enron.com",
      "x-from": "Enron General Announcements"
   },
   {
      "Foldername": "junk_file",
      "filename": "480_",
      "from": "energyreleases@excite.com",
      "x-from": "EnergyReleases"
   },
   {
      "Foldername": "junk_file",
      "filename": "481_",
      "from": "lippmanc@aol.com",
      "x-from": "Lippmanc@aol.com"
   },
   {
      "Foldername": "junk_file",
      "filename": "482_",
      "from": "bruno@firstconf.com",
      "x-from": "Bruno Russell"
   },
   {
      "Foldername": "junk_file",
      "filename": "483_",
      "from": "dennis.lee@enron.com",
      "x-from": "Lee, Dennis"
   },
   {
      "Foldername": "junk_file",
      "filename": "484_",
      "from": "audrey.robertson@enron.com",
      "x-from": "Robertson, Audrey"
   },
   {
      "Foldername": "junk_file",
      "filename": "486_",
      "from": "paul.cherry@enron.com",
      "x-from": "Cherry, Paul"
   },
   {
      "Foldername": "junk_file",
      "filename": "487_",
      "from": "steven.harris@enron.com",
      "x-from": "Harris, Steven"
   },
   {
      "Foldername": "junk_file",
      "filename": "488_",
      "from": "dennis.lee@enron.com",
      "x-from": "Lee, Dennis"
   },
   {
      "Foldername": "junk_file",
      "filename": "489_",
      "from": "newsletter@rigzone.com",
      "x-from": "newsletter@rigzone.com"
   },
   {
      "Foldername": "junk_file",
      "filename": "48_",
      "from": "newsletter@rigzone.com",
      "x-from": "newsletter@rigzone.com"
   },
   {
      "Foldername": "junk_file",
      "filename": "491_",
      "from": "info@pmaconference.com",
      "x-from": "The Power Marketing Association"
   },
   {
      "Foldername": "junk_file",
      "filename": "492_",
      "from": "center.ets@enron.com",
      "x-from": "ETS Solution Center"
   },
   {
      "Foldername": "junk_file",
      "filename": "493_",
      "from": "notification.isc@enron.com",
      "x-from": "ISC Systems Notification"
   },
   {
      "Foldername": "junk_file",
      "filename": "494_",
      "from": "energymarkets@halldata.com",
      "x-from": "Energy Markets"
   },
   {
      "Foldername": "junk_file",
      "filename": "496_",
      "from": "info@pmaconference.com",
      "x-from": "The Power Marketing Association"
   },
   {
      "Foldername": "junk_file",
      "filename": "497_",
      "from": "newsletter@rigzone.com",
      "x-from": "newsletter@rigzone.com"
   },
   {
      "Foldername": "junk_file",
      "filename": "499_",
      "from": "info@global-change.com",
      "x-from": "info@global-change.com"
   },
   {
      "Foldername": "junk_file",
      "filename": "4_",
      "from": "tk.lohman@enron.com",
      "x-from": "Lohman, TK"
   },
   {
      "Foldername": "junk_file",
      "filename": "500_",
      "from": "center.ets@enron.com",
      "x-from": "ETS Solution Center"
   },
   {
      "Foldername": "junk_file",
      "filename": "501_",
      "from": "newsletter@rigzone.com",
      "x-from": "newsletter@rigzone.com"
   },
   {
      "Foldername": "junk_file",
      "filename": "503_",
      "from": "center.ets@enron.com",
      "x-from": "ETS Solution Center"
   },
   {
      "Foldername": "junk_file",
      "filename": "504_",
      "from": "lippmanc@aol.com",
      "x-from": "Lippmanc@aol.com"
   },
   {
      "Foldername": "junk_file",
      "filename": "505_",
      "from": "talbots@clickaction.net",
      "x-from": "talbots.com"
   },
   {
      "Foldername": "junk_file",
      "filename": "506_",
      "from": "announcements.egs@enron.com",
      "x-from": "EGS General Announcements"
   },
   {
      "Foldername": "junk_file",
      "filename": "507_",
      "from": "center.ets@enron.com",
      "x-from": "ETS Solution Center"
   },
   {
      "Foldername": "junk_file",
      "filename": "508_",
      "from": "j.jill@service.jjill.com",
      "x-from": "J.Jill"
   },
   {
      "Foldername": "junk_file",
      "filename": "509_",
      "from": "newsletter@rigzone.com",
      "x-from": "newsletter@rigzone.com"
   },
   {
      "Foldername": "junk_file",
      "filename": "50_",
      "from": "kevin.hyatt@enron.com",
      "x-from": "Hyatt, Kevin"
   },
   {
      "Foldername": "junk_file",
      "filename": "511_",
      "from": "davis.thames@enron.com",
      "x-from": "Thames, Davis"
   },
   {
      "Foldername": "junk_file",
      "filename": "512_",
      "from": "a..howard@enron.com",
      "x-from": "Howard, Kevin A."
   },
   {
      "Foldername": "junk_file",
      "filename": "513_",
      "from": "steven.harris@enron.com",
      "x-from": "Harris, Steven"
   },
   {
      "Foldername": "junk_file",
      "filename": "514_",
      "from": "a..howard@enron.com",
      "x-from": "Howard, Kevin A."
   },
   {
      "Foldername": "junk_file",
      "filename": "515_",
      "from": "a..howard@enron.com",
      "x-from": "Howard, Kevin A."
   },
   {
      "Foldername": "junk_file",
      "filename": "516_",
      "from": "a..howard@enron.com",
      "x-from": "Howard, Kevin A."
   },
   {
      "Foldername": "junk_file",
      "filename": "517_",
      "from": "denis.tu@enron.com",
      "x-from": "Tu, Denis"
   },
   {
      "Foldername": "junk_file",
      "filename": "518_",
      "from": "teb.lokey@enron.com",
      "x-from": "Lokey, Teb"
   },
   {
      "Foldername": "junk_file",
      "filename": "519_",
      "from": "announcements.enron@enron.com",
      "x-from": "Enron General Announcements"
   },
   {
      "Foldername": "junk_file",
      "filename": "51_",
      "from": "dennis.lee@enron.com",
      "x-from": "Lee, Dennis"
   },
   {
      "Foldername": "junk_file",
      "filename": "520_",
      "from": "e..rosenberg@enron.com",
      "x-from": "Rosenberg, David E."
   },
   {
      "Foldername": "junk_file",
      "filename": "521_",
      "from": "l..eisenstein@enron.com",
      "x-from": "Eisenstein, Arnold L."
   },
   {
      "Foldername": "junk_file",
      "filename": "522_",
      "from": "denis.tu@enron.com",
      "x-from": "Tu, Denis"
   },
   {
      "Foldername": "junk_file",
      "filename": "524_",
      "from": "newsletter@rigzone.com",
      "x-from": "newsletter@rigzone.com"
   },
   {
      "Foldername": "junk_file",
      "filename": "527_",
      "from": "executive.office@enron.com",
      "x-from": "Office of the Chief Executive"
   },
   {
      "Foldername": "junk_file",
      "filename": "528_",
      "from": "dennis.lee@enron.com",
      "x-from": "Lee, Dennis"
   },
   {
      "Foldername": "junk_file",
      "filename": "529_",
      "from": "kimberly.watson@enron.com",
      "x-from": "Watson, Kimberly"
   },
   {
      "Foldername": "junk_file",
      "filename": "52_",
      "from": "dennis.lee@enron.com",
      "x-from": "Lee, Dennis"
   },
   {
      "Foldername": "junk_file",
      "filename": "530_",
      "from": "ann.foret@enron.com",
      "x-from": "Foret, Leigh Ann"
   },
   {
      "Foldername": "junk_file",
      "filename": "531_",
      "from": "denis.tu@enron.com",
      "x-from": "Tu, Denis"
   },
   {
      "Foldername": "junk_file",
      "filename": "532_",
      "from": "audrey.robertson@enron.com",
      "x-from": "Robertson, Audrey"
   },
   {
      "Foldername": "junk_file",
      "filename": "533_",
      "from": "ron.matthews@enron.com",
      "x-from": "Matthews, Ron"
   },
   {
      "Foldername": "junk_file",
      "filename": "534_",
      "from": "newsletter@rigzone.com",
      "x-from": "newsletter@rigzone.com"
   },
   {
      "Foldername": "junk_file",
      "filename": "536_",
      "from": "wayne.feng@enron.com",
      "x-from": "Feng, Wayne"
   },
   {
      "Foldername": "junk_file",
      "filename": "537_",
      "from": "ramona.betancourt@enron.com",
      "x-from": "Betancourt, Ramona"
   },
   {
      "Foldername": "junk_file",
      "filename": "538_",
      "from": "kelly.allen@enron.com",
      "x-from": "Allen, Kelly"
   },
   {
      "Foldername": "junk_file",
      "filename": "539_",
      "from": "r-7-738070-4601862-2-1011-us1-68dd993f@xmr3.com",
      "x-from": "Energy and Environmental Analysis"
   },
   {
      "Foldername": "junk_file",
      "filename": "53_",
      "from": "audrey.robertson@enron.com",
      "x-from": "Robertson, Audrey"
   },
   {
      "Foldername": "junk_file",
      "filename": "540_",
      "from": "dennis.lee@enron.com",
      "x-from": "Lee, Dennis"
   },
   {
      "Foldername": "junk_file",
      "filename": "541_",
      "from": "audrey.robertson@enron.com",
      "x-from": "Robertson, Audrey"
   },
   {
      "Foldername": "junk_file",
      "filename": "542_",
      "from": "lippmanc@aol.com",
      "x-from": "Lippmanc@aol.com"
   },
   {
      "Foldername": "junk_file",
      "filename": "543_",
      "from": "adamsholly@netscape.net",
      "x-from": "holly adams"
   },
   {
      "Foldername": "junk_file",
      "filename": "544_",
      "from": "elizabeth.brown@enron.com",
      "x-from": "Brown, Elizabeth"
   },
   {
      "Foldername": "junk_file",
      "filename": "545_",
      "from": "ron.matthews@enron.com",
      "x-from": "Matthews, Ron"
   },
   {
      "Foldername": "junk_file",
      "filename": "546_",
      "from": "jan.moore@enron.com",
      "x-from": "Moore, Jan"
   },
   {
      "Foldername": "junk_file",
      "filename": "547_",
      "from": "lorraine.lindberg@enron.com",
      "x-from": "Lindberg, Lorraine"
   },
   {
      "Foldername": "junk_file",
      "filename": "548_",
      "from": "susan.wadle@enron.com",
      "x-from": "Wadle, Susan"
   },
   {
      "Foldername": "junk_file",
      "filename": "549_",
      "from": "michael.ratner@enron.com",
      "x-from": "Ratner, Michael"
   },
   {
      "Foldername": "junk_file",
      "filename": "54_",
      "from": "mark.mcconnell@enron.com",
      "x-from": "McConnell, Mark"
   },
   {
      "Foldername": "junk_file",
      "filename": "550_",
      "from": "kelly.allen@enron.com",
      "x-from": "Allen, Kelly"
   },
   {
      "Foldername": "junk_file",
      "filename": "551_",
      "from": "ramona.betancourt@enron.com",
      "x-from": "Betancourt, Ramona"
   },
   {
      "Foldername": "junk_file",
      "filename": "552_",
      "from": "kevin.hyatt@enron.com",
      "x-from": "Hyatt, Kevin"
   },
   {
      "Foldername": "junk_file",
      "filename": "553_",
      "from": "announcements.enron@enron.com",
      "x-from": "Enron General Announcements"
   },
   {
      "Foldername": "junk_file",
      "filename": "554_",
      "from": "linda.trevino@enron.com",
      "x-from": "Trevino, Linda"
   },
   {
      "Foldername": "junk_file",
      "filename": "555_",
      "from": "jeanette.doll@enron.com",
      "x-from": "Doll, Jeanette"
   },
   {
      "Foldername": "junk_file",
      "filename": "556_",
      "from": "ruthann.frausto@enron.com",
      "x-from": "Frausto, Ruthann"
   },
   {
      "Foldername": "junk_file",
      "filename": "557_",
      "from": "michelle.lokay@enron.com",
      "x-from": "Lokay, Michelle"
   },
   {
      "Foldername": "junk_file",
      "filename": "558_",
      "from": "jan.moore@enron.com",
      "x-from": "Moore, Jan"
   },
   {
      "Foldername": "junk_file",
      "filename": "559_",
      "from": "tk.lohman@enron.com",
      "x-from": "Lohman, TK"
   },
   {
      "Foldername": "junk_file",
      "filename": "55_",
      "from": "administration.enron@enron.com",
      "x-from": "Enron Messaging Administration"
   },
   {
      "Foldername": "junk_file",
      "filename": "560_",
      "from": "steven.harris@enron.com",
      "x-from": "Harris, Steven"
   },
   {
      "Foldername": "junk_file",
      "filename": "561_",
      "from": "a..howard@enron.com",
      "x-from": "Howard, Kevin A."
   },
   {
      "Foldername": "junk_file",
      "filename": "562_",
      "from": "michael.ratner@enron.com",
      "x-from": "Ratner, Michael"
   },
   {
      "Foldername": "junk_file",
      "filename": "563_",
      "from": "michael.ratner@enron.com",
      "x-from": "Ratner, Michael"
   },
   {
      "Foldername": "junk_file",
      "filename": "564_",
      "from": "glen.hass@enron.com",
      "x-from": "Hass, Glen"
   },
   {
      "Foldername": "junk_file",
      "filename": "565_",
      "from": "lorraine.lindberg@enron.com",
      "x-from": "Lindberg, Lorraine"
   },
   {
      "Foldername": "junk_file",
      "filename": "566_",
      "from": "robert.kilmer@enron.com",
      "x-from": "Kilmer III, Robert"
   },
   {
      "Foldername": "junk_file",
      "filename": "567_",
      "from": "ramona.betancourt@enron.com",
      "x-from": "Betancourt, Ramona"
   },
   {
      "Foldername": "junk_file",
      "filename": "568_",
      "from": "tickets-email@onsale.ticketmaster.com",
      "x-from": "tickets-email@onsale.ticketmaster.com"
   },
   {
      "Foldername": "junk_file",
      "filename": "569_",
      "from": "paul.y'barbo@enron.com",
      "x-from": "Y'barbo, Paul"
   },
   {
      "Foldername": "junk_file",
      "filename": "56_",
      "from": "dennis.lee@enron.com",
      "x-from": "Lee, Dennis"
   },
   {
      "Foldername": "junk_file",
      "filename": "57_",
      "from": "lorna.brennan@enron.com",
      "x-from": "Brennan, Lorna"
   },
   {
      "Foldername": "junk_file",
      "filename": "58_",
      "from": "julie.mccoy@enron.com",
      "x-from": "McCoy, Julie"
   },
   {
      "Foldername": "junk_file",
      "filename": "59_",
      "from": "audrey.robertson@enron.com",
      "x-from": "Robertson, Audrey"
   },
   {
      "Foldername": "junk_file",
      "filename": "5_",
      "from": "audrey.robertson@enron.com",
      "x-from": "Robertson, Audrey"
   },
   {
      "Foldername": "junk_file",
      "filename": "60_",
      "from": "elizabeth.brown@enron.com",
      "x-from": "Brown, Elizabeth"
   },
   {
      "Foldername": "junk_file",
      "filename": "61_",
      "from": "michelle.lokay@enron.com",
      "x-from": "Lokay, Michelle"
   },
   {
      "Foldername": "junk_file",
      "filename": "62_",
      "from": "michelle.lokay@enron.com",
      "x-from": "Lokay, Michelle"
   },
   {
      "Foldername": "junk_file",
      "filename": "63_",
      "from": "glen.hass@enron.com",
      "x-from": "Hass, Glen"
   },
   {
      "Foldername": "junk_file",
      "filename": "64_",
      "from": "elizabeth.brown@enron.com",
      "x-from": "Brown, Elizabeth"
   },
   {
      "Foldername": "junk_file",
      "filename": "65_",
      "from": "lorna.brennan@enron.com",
      "x-from": "Brennan, Lorna"
   },
   {
      "Foldername": "junk_file",
      "filename": "66_",
      "from": "kimberly.watson@enron.com",
      "x-from": "Watson, Kimberly"
   },
   {
      "Foldername": "junk_file",
      "filename": "67_",
      "from": "chairman.enron@enron.com",
      "x-from": "Enron Office Of The Chairman"
   },
   {
      "Foldername": "junk_file",
      "filename": "68_",
      "from": "linda.wehring@enron.com",
      "x-from": "Wehring, Linda"
   },
   {
      "Foldername": "junk_file",
      "filename": "69_",
      "from": "elizabeth.brown@enron.com",
      "x-from": "Brown, Elizabeth"
   },
   {
      "Foldername": "junk_file",
      "filename": "6_",
      "from": "no.address@enron.com",
      "x-from": "Enron Corporate Administrative Services@ENRON"
   },
   {
      "Foldername": "junk_file",
      "filename": "70_",
      "from": "craig.buehler@enron.com",
      "x-from": "Buehler, Craig"
   },
   {
      "Foldername": "junk_file",
      "filename": "71_",
      "from": "glen.hass@enron.com",
      "x-from": "Hass, Glen"
   },
   {
      "Foldername": "junk_file",
      "filename": "72_",
      "from": "elizabeth.brown@enron.com",
      "x-from": "Brown, Elizabeth"
   },
   {
      "Foldername": "junk_file",
      "filename": "73_",
      "from": "richard.riehm@enron.com",
      "x-from": "Riehm, Richard"
   },
   {
      "Foldername": "junk_file",
      "filename": "74_",
      "from": "elizabeth.brown@enron.com",
      "x-from": "Brown, Elizabeth"
   },
   {
      "Foldername": "junk_file",
      "filename": "75_",
      "from": "dennis.lee@enron.com",
      "x-from": "Lee, Dennis"
   },
   {
      "Foldername": "junk_file",
      "filename": "77_",
      "from": "news@eyeforenergy.com",
      "x-from": "news@eyeforenergy.com"
   },
   {
      "Foldername": "junk_file",
      "filename": "78_",
      "from": "newsletter@rigzone.com",
      "x-from": "newsletter@rigzone.com"
   },
   {
      "Foldername": "junk_file",
      "filename": "79_",
      "from": "center.ets@enron.com",
      "x-from": "ETS Solution Center"
   },
   {
      "Foldername": "junk_file",
      "filename": "7_",
      "from": "announcements.enron@enron.com",
      "x-from": "Enron General Announcements"
   },
   {
      "Foldername": "junk_file",
      "filename": "80_",
      "from": "info@pmaconference.com",
      "x-from": "The Power Marketing Association"
   },
   {
      "Foldername": "junk_file",
      "filename": "81_",
      "from": "email@email.themoment.com",
      "x-from": "Platform for Real-time Trading"
   },
   {
      "Foldername": "junk_file",
      "filename": "82_",
      "from": "ben.asante@enron.com",
      "x-from": "Asante, Ben"
   },
   {
      "Foldername": "junk_file",
      "filename": "83_",
      "from": "kimberly.watson@enron.com",
      "x-from": "Watson, Kimberly"
   },
   {
      "Foldername": "junk_file",
      "filename": "84_",
      "from": "michelle.lokay@enron.com",
      "x-from": "Lokay, Michelle"
   },
   {
      "Foldername": "junk_file",
      "filename": "85_",
      "from": "chairman.enron@enron.com",
      "x-from": "Enron Office Of The Chairman"
   },
   {
      "Foldername": "junk_file",
      "filename": "86_",
      "from": "jr..legal@enron.com",
      "x-from": "Legal - James Derrick Jr."
   },
   {
      "Foldername": "junk_file",
      "filename": "87_",
      "from": "newsletter@rigzone.com",
      "x-from": "newsletter@rigzone.com"
   },
   {
      "Foldername": "junk_file",
      "filename": "89_",
      "from": "info@pmaconference.com",
      "x-from": "The Power Marketing Association"
   },
   {
      "Foldername": "junk_file",
      "filename": "8_",
      "from": "jjill@clickaction.net",
      "x-from": "J. Jill"
   },
   {
      "Foldername": "junk_file",
      "filename": "90_",
      "from": "announcements.enron@enron.com",
      "x-from": "Enron General Announcements"
   },
   {
      "Foldername": "junk_file",
      "filename": "91_",
      "from": "central.communication@enron.com",
      "x-from": "Communication Central"
   },
   {
      "Foldername": "junk_file",
      "filename": "92_",
      "from": "center.ets@enron.com",
      "x-from": "ETS Solution Center"
   },
   {
      "Foldername": "junk_file",
      "filename": "93_",
      "from": "gasmart@gasmart.com",
      "x-from": "Gasmart@Gasmart.com"
   },
   {
      "Foldername": "junk_file",
      "filename": "94_",
      "from": "central.communication@enron.com",
      "x-from": "Communication Central"
   },
   {
      "Foldername": "junk_file",
      "filename": "95_",
      "from": "info@pmaconference.com",
      "x-from": "The Power Marketing Association"
   },
   {
      "Foldername": "junk_file",
      "filename": "96_",
      "from": "newsletter@rigzone.com",
      "x-from": "newsletter@rigzone.com"
   },
   {
      "Foldername": "junk_file",
      "filename": "97_",
      "from": "lippmanc@aol.com",
      "x-from": "Lippmanc@aol.com"
   },
   {
      "Foldername": "junk_file",
      "filename": "98_",
      "from": "dennis.lee@enron.com",
      "x-from": "Lee, Dennis"
   },
   {
      "Foldername": "junk_file",
      "filename": "99_",
      "from": "dennis.lee@enron.com",
      "x-from": "Lee, Dennis"
   },
   {
      "Foldername": "junk_file",
      "filename": "9_",
      "from": "angela.white@enron.com",
      "x-from": "White, Angela"
   }
]